glan2_dedup/__init__.py
glan2_dedup/build.py
glan2_dedup/build_test.py
glan2_dedup/minhash_index.py
glan2_dedup-0.1.0.dist-info/METADATA
glan2_dedup-0.1.0.dist-info/WHEEL
glan2_dedup-0.1.0.dist-info/top_level.txt
glan2_dedup-0.1.0.dist-info/RECORD
